analogues/__init__.py
analogues/analogues.py
analogues-0.0.1.dist-info/METADATA
analogues-0.0.1.dist-info/WHEEL
analogues-0.0.1.dist-info/licenses/LICENSE
analogues-0.0.1.dist-info/RECORD
