Metadata-Version: 2.3
Name: analogues
Version: 0.0.1
Summary: Estimate analogue historic climatic conditions
Project-URL: Homepage, https://github.com/MutaharChalmers/analogues
Author-email: Mutahar Chalmers <mutahar.chalmers@gmail.com>
License: MIT License
License-File: LICENSE
Classifier: Development Status :: 4 - Beta
Classifier: Intended Audience :: Science/Research
Classifier: License :: OSI Approved :: MIT License
Classifier: Operating System :: OS Independent
Classifier: Programming Language :: Python :: 3
Classifier: Topic :: Scientific/Engineering
Requires-Python: >=3.8
Requires-Dist: numpy>=1.18
Requires-Dist: pandas>=1.0
Requires-Dist: quadgrid>=0.1.4
Requires-Dist: scikit-learn>=0.18
Requires-Dist: scipy>=1.10
Requires-Dist: xarray>=2023.01.0
